photoscope
